sqlalchemy_utils/__init__.py
sqlalchemy_utils/aggregates.py
sqlalchemy_utils/asserts.py
sqlalchemy_utils/compat.py
sqlalchemy_utils/exceptions.py
sqlalchemy_utils/expressions.py
sqlalchemy_utils/generic.py
sqlalchemy_utils/i18n.py
sqlalchemy_utils/listeners.py
sqlalchemy_utils/models.py
sqlalchemy_utils/observer.py
sqlalchemy_utils/operators.py
sqlalchemy_utils/path.py
sqlalchemy_utils/proxy_dict.py
sqlalchemy_utils/query_chain.py
sqlalchemy_utils/utils.py
sqlalchemy_utils/view.py
sqlalchemy_utils/functions/__init__.py
sqlalchemy_utils/functions/database.py
sqlalchemy_utils/functions/foreign_keys.py
sqlalchemy_utils/functions/mock.py
sqlalchemy_utils/functions/orm.py
sqlalchemy_utils/functions/render.py
sqlalchemy_utils/functions/sort_query.py
sqlalchemy_utils/primitives/__init__.py
sqlalchemy_utils/primitives/country.py
sqlalchemy_utils/primitives/currency.py
sqlalchemy_utils/primitives/ltree.py
sqlalchemy_utils/primitives/weekday.py
sqlalchemy_utils/primitives/weekdays.py
sqlalchemy_utils/relationships/__init__.py
sqlalchemy_utils/relationships/chained_join.py
sqlalchemy_utils/types/__init__.py
sqlalchemy_utils/types/arrow.py
sqlalchemy_utils/types/bit.py
sqlalchemy_utils/types/choice.py
sqlalchemy_utils/types/color.py
sqlalchemy_utils/types/country.py
sqlalchemy_utils/types/currency.py
sqlalchemy_utils/types/email.py
sqlalchemy_utils/types/ip_address.py
sqlalchemy_utils/types/json.py
sqlalchemy_utils/types/locale.py
sqlalchemy_utils/types/ltree.py
sqlalchemy_utils/types/password.py
sqlalchemy_utils/types/pg_composite.py
sqlalchemy_utils/types/phone_number.py
sqlalchemy_utils/types/range.py
sqlalchemy_utils/types/scalar_coercible.py
sqlalchemy_utils/types/scalar_list.py
sqlalchemy_utils/types/timezone.py
sqlalchemy_utils/types/ts_vector.py
sqlalchemy_utils/types/url.py
sqlalchemy_utils/types/uuid.py
sqlalchemy_utils/types/weekdays.py
sqlalchemy_utils/types/encrypted/__init__.py
sqlalchemy_utils/types/encrypted/encrypted_type.py
SQLAlchemy_Utils-0.41.2.dist-info/LICENSE
SQLAlchemy_Utils-0.41.2.dist-info/METADATA
SQLAlchemy_Utils-0.41.2.dist-info/WHEEL
SQLAlchemy_Utils-0.41.2.dist-info/top_level.txt
SQLAlchemy_Utils-0.41.2.dist-info/RECORD
